topicextractor/__init__.py
topicextractor-0.0.2.dist-info/LICENSE
topicextractor-0.0.2.dist-info/METADATA
topicextractor-0.0.2.dist-info/WHEEL
topicextractor-0.0.2.dist-info/top_level.txt
topicextractor-0.0.2.dist-info/RECORD
