Metadata-Version: 2.1
Name: topicextractor
Version: 0.0.2
Summary: Extracts keywords with 'TF-IDF' algorithm
Home-page: https://github.com/kjchung495/topicextractor
Author: KJ Chung
Author-email: kjchung495@yonsei.ac.kr
License: Apache Software License 2.0
Keywords: TFIDF,topic analysis
Platform: UNKNOWN
Classifier: Intended Audience :: Science/Research
Classifier: License :: OSI Approved :: Apache Software License
Classifier: Programming Language :: Python :: 3
